<?xml version="1.0" encoding="UTF-8"?>
<!DOCTYPE mapper PUBLIC "-//mybatis.org//DTD Mapper 3.0//EN" "http://mybatis.org/dtd/mybatis-3-mapper.dtd">
<mapper namespace="com.jielin.message.dao.mysql.GtAliasDao">
    <resultMap id="BaseResultMap" type="com.jielin.message.po.GtAliasPo">
        <!--
          WARNING - @mbg.generated
          This element is automatically generated by MyBatis Generator, do not modify.
          This element was generated on Tue Oct 08 17:19:36 CST 2019.
        -->
        <result column="id" jdbcType="INTEGER" property="id"/>
        <result column="cid" jdbcType="VARCHAR" property="cid"/>
        <result column="alias" jdbcType="VARCHAR" property="alias"/>
        <result column="app_type" jdbcType="VARCHAR" property="appType"/>
        <result column="phone" jdbcType="VARCHAR" property="phone"/>
    </resultMap>
    <sql id="Base_Column_List">
        <!--
          WARNING - @mbg.generated
          This element is automatically generated by MyBatis Generator, do not modify.
          This element was generated on Tue Oct 08 17:19:36 CST 2019.
        -->
        id, cid, alias, app_type, phone
    </sql>
    <insert id="insert" parameterType="com.jielin.message.po.GtAliasPo">
        <!--
          WARNING - @mbg.generated
          This element is automatically generated by MyBatis Generator, do not modify.
          This element was generated on Tue Oct 08 17:19:36 CST 2019.
        -->
        insert into jl_gt_alias (id, cid, alias, app_type, phone)
        values (#{id,jdbcType=INTEGER}, #{cid,jdbcType=VARCHAR}, #{alias,jdbcType=VARCHAR}, #{appType,jdbcType=VARCHAR},
        #{phone,jdbcType=VARCHAR})
    </insert>
    <select id="selectByCid" parameterType="string" resultType="com.jielin.message.po.GtAliasPo">
        select
        <include refid="Base_Column_List"/>
        from jl_gt_alias
        where cid = #{cid} and app_type = #{appType} and phone = #{phone}
    </select>
    <select id="selectByCidAndAppType" parameterType="string" resultType="com.jielin.message.po.GtAliasPo">
        select
        <include refid="Base_Column_List"/>
        from jl_gt_alias
        where cid = #{cid} and app_type = #{appType}
    </select>
    <select id="selectAliasByPhone" resultType="java.lang.String">
        select alias from jl_gt_alias
        where app_type = #{appType} and phone = #{phone}
        LIMIT 1
    </select>
    <!--批量删除用户-->
    <delete id="deleteByIds" parameterType="java.util.List">
        delete from jl_gt_alias where id IN
        <foreach collection="ids" item="id" index="index" open="(" close=")" separator=",">
            #{id}
        </foreach>
    </delete>
</mapper>